einkd/__init__.py
einkd/display.py
einkd/py.typed
einkd/drivers/__init__.py
einkd/drivers/base.py
einkd/drivers/epd2in13bc.py
einkd/drivers/virtual.py
einkd/gui/__init__.py
einkd/gui/window.py
einkd/gui/components/__init__.py
einkd/gui/components/component.py
einkd/gui/components/filled.py
einkd/gui/components/image.py
einkd/gui/components/text.py
einkd-0.1.2.dist-info/LICENCE
einkd-0.1.2.dist-info/METADATA
einkd-0.1.2.dist-info/WHEEL
einkd-0.1.2.dist-info/top_level.txt
einkd-0.1.2.dist-info/RECORD
