Metadata-Version: 2.1
Name: einkd
Version: 0.1.2
Summary: A daemon and library for displaying images on e-ink displays.
Home-page: https://github.com/trickeydan/einkd
Author: Dan Trickey
License: MIT
Platform: UNKNOWN
Classifier: Topic :: Software Development
Classifier: Typing :: Typed
Requires-Python: >=3.7
License-File: LICENCE
Requires-Dist: pillow (>=8.0.0)
Provides-Extra: epdrpi
Requires-Dist: RPi.GPIO ; extra == 'epdrpi'
Requires-Dist: spidev ; extra == 'epdrpi'
